corava/__init__.py
corava/audio_util.py
corava/aws_services.py
corava/cora.py
corava/cora_config.py
corava/cora_memory.py
corava/cora_skills.py
corava/cora_visualiser.py
corava/openai_services.py
corava/utilities.py
corava-0.2.5.dist-info/entry_points.txt
corava-0.2.5.dist-info/LICENSE
corava-0.2.5.dist-info/METADATA
corava-0.2.5.dist-info/WHEEL
corava-0.2.5.dist-info/RECORD
