Metadata-Version: 2.1
Name: corava
Version: 0.2.5
Summary: Python project for development of a Conversation Optimized Robot Assistant (CORA). CORA is a voice assistant that is powered by openai's chatgpt for both user intent detection as well as general LLM responses.
License: MIT
Author: Nicholas Chai
Author-email: nicholas.chai@outlook.com
Requires-Python: >=3.10,<3.13
Classifier: License :: OSI Approved :: MIT License
Classifier: Programming Language :: Python :: 3
Classifier: Programming Language :: Python :: 3.10
Classifier: Programming Language :: Python :: 3.11
Classifier: Programming Language :: Python :: 3.12
Requires-Dist: boto3 (>=1.28.78,<2.0.0)
Requires-Dist: openai (>=1.2.0,<2.0.0)
Requires-Dist: openai-whisper (==20231106)
Requires-Dist: pyaudio (>=0.2.13,<0.3.0)
Requires-Dist: pydub (>=0.25.1,<0.26.0)
Requires-Dist: pygame (>=2.5.2,<3.0.0)
Requires-Dist: python-dotenv (>=1.0.0,<2.0.0)
Requires-Dist: simpleaudio (>=1.0.4,<2.0.0)
Requires-Dist: soundfile (>=0.12.1,<0.13.0)
Requires-Dist: speechrecognition (>=3.10.0,<4.0.0)
